{
  "id": "19-brazos-del-padre",
  "number": 19,
  "title": "Brazos del Padre",
  "slug": "brazos-del-padre",
  "startPage": 250,
  "endPage": 262,
  "verses": [
    {
      "number": 1,
      "type": "verse",
      "content": "Conozco un lugar, donde yo\nNecesito por siempre habitar\nEs un lugar de descanso y paz"
    },
    {
      "number": 2,
      "type": "verse",
      "content": "Donde el gozo nunca falta\nY tu amor fluye en libertad"
    },
    {
      "number": 3,
      "type": "verse",
      "content": "Nada me falta cuando\nen tus ojos veo el amor\nY sé que es para mí"
    },
    {
      "number": 4,
      "type": "verse",
      "content": "Y no tengo temor\ncuando estoy en\nlos brazos del Padre"
    },
    {
      "number": 5,
      "type": "verse",
      "content": "Y si llego a caer\nme consuela el saber que\nTu estas aquí"
    },
    {
      "number": 6,
      "type": "verse",
      "content": "Conozco un lugar, donde yo\nNecesito por siempre habitar\nEs un lugar de descanso y paz"
    },
    {
      "number": 7,
      "type": "verse",
      "content": "Donde el gozo nunca falta\nY tu amor fluye en libertad"
    },
    {
      "number": 8,
      "type": "verse",
      "content": "Nada me falta cuando\nen tus ojos veo el amor\nY sé que es para mí"
    },
    {
      "number": 9,
      "type": "verse",
      "content": "Y no tengo temor\ncuando estoy en\nlos brazos del Padre"
    },
    {
      "number": 10,
      "type": "verse",
      "content": "Y si llego a caer\nme consuela el saber que\nTu estas aquí"
    },
    {
      "number": 11,
      "type": "verse",
      "content": "Yo no tengo temor\ncuando estoy en\nlos brazos del Padre"
    },
    {
      "number": 12,
      "type": "verse",
      "content": "Y si llego a caer\nme consuela el saber que\nTu estas aquí"
    }
  ],
  "metadata": {
    "verseCount": 12,
    "hasChorus": false,
    "source": "pdf",
    "extractedAt": "2026-01-06T14:37:32.583940"
  }
}